apollopy/__init__.py
apollopy/config.py
apollopy-1.1.2.dist-info/LICENSE
apollopy-1.1.2.dist-info/METADATA
apollopy-1.1.2.dist-info/WHEEL
apollopy-1.1.2.dist-info/entry_points.txt
apollopy-1.1.2.dist-info/top_level.txt
apollopy-1.1.2.dist-info/RECORD
