Metadata-Version: 2.1
Name: apollopy
Version: 1.1.2
Summary: A basic CLI tool which helps you being healthy.
Home-page: https://bitbucket.org/shravannn/apollo/
Author: Shravan Asati
Author-email: dev.shravan@protonmail.com
License: BSD
Platform: UNKNOWN
Requires-Dist: plyer
Requires-Dist: click
Requires-Dist: pyttsx3
